src/__init__.py
src/__main__.py
src/analyzer.py
src/arguments.py
src/constants.py
src/doc_similarity.py
src/get_handler.py
src/json_util.py
src/markdown.py
src/summarizer.py
src/topic_modeling.py
src/visualization.py
GatorMiner-1.0.0.dist-info/LICENSE
GatorMiner-1.0.0.dist-info/METADATA
GatorMiner-1.0.0.dist-info/WHEEL
GatorMiner-1.0.0.dist-info/top_level.txt
GatorMiner-1.0.0.dist-info/RECORD
