Metadata-Version: 2.1
Name: GatorMiner
Version: 1.0.0
Summary: An automatic text mining tool
Home-page: https://github.com/Allegheny-Ethical-CS/GatorMiner
Author: Enpu You
Author-email: youe2@allegheny.edu
License: UNKNOWN
Platform: UNKNOWN
Requires-Dist: Git
Requires-Dist: Pipenv
Requires-Dist: en-core-web-sm
Requires-Dist: en-core-web-md
